src/__init__.py
src/azcred.py
src/azvaultcopy.py
src/config.py
src/dir.py
src/export_import.py
src/log.py
src/model.py
src/report.py
src/util.py
src/vault.py
src/tests/__init__.py
src/tests/cert_report_stats_test.py
src/tests/vault_cert_test.py
src/tests/vault_secret_test.py
azvaultcopy-1.0.0b1.dist-info/LICENSE
azvaultcopy-1.0.0b1.dist-info/METADATA
azvaultcopy-1.0.0b1.dist-info/WHEEL
azvaultcopy-1.0.0b1.dist-info/entry_points.txt
azvaultcopy-1.0.0b1.dist-info/top_level.txt
azvaultcopy-1.0.0b1.dist-info/RECORD
